[{"model": "admin.logentry", "pk": 1, "fields": {"action_time": "2022-11-21T03:45:15.877Z", "user": 1, "content_type": 8, "object_id": "1", "object_repr": "Familia", "action_flag": 1, "change_message": "[{\"added\": {}}]"}}, {"model": "admin.logentry", "pk": 2, "fields": {"action_time": "2022-11-21T03:46:45.431Z", "user": 1, "content_type": 7, "object_id": "1", "object_repr": "Cuándo y cómo lavarse las manos", "action_flag": 1, "change_message": "[{\"added\": {}}]"}}, {"model": "admin.logentry", "pk": 3, "fields": {"action_time": "2022-11-21T03:46:48.908Z", "user": 1, "content_type": 6, "object_id": "1", "object_repr": "Página de inicio", "action_flag": 1, "change_message": "[{\"added\": {}}]"}}, {"model": "admin.logentry", "pk": 4, "fields": {"action_time": "2022-11-21T03:54:00.157Z", "user": 1, "content_type": 6, "object_id": "1", "object_repr": "Página de inicio", "action_flag": 2, "change_message": "[{\"changed\": {\"fields\": [\"Youtube video link\"]}}]"}}, {"model": "admin.logentry", "pk": 5, "fields": {"action_time": "2022-11-21T04:22:59.563Z", "user": 1, "content_type": 8, "object_id": "2", "object_repr": "manada", "action_flag": 1, "change_message": "[{\"added\": {}}]"}}, {"model": "admin.logentry", "pk": 6, "fields": {"action_time": "2022-11-21T04:31:24.413Z", "user": 1, "content_type": 6, "object_id": "1", "object_repr": "Página de inicio", "action_flag": 2, "change_message": "[{\"changed\": {\"fields\": [\"Imagen del banner del inicio\"]}}]"}}, {"model": "admin.logentry", "pk": 7, "fields": {"action_time": "2022-11-21T04:31:30.890Z", "user": 1, "content_type": 7, "object_id": "1", "object_repr": "Cuándo y cómo lavarse las manos", "action_flag": 2, "change_message": "[{\"changed\": {\"fields\": [\"Imagen\"]}}]"}}, {"model": "admin.logentry", "pk": 8, "fields": {"action_time": "2022-11-21T04:31:36.570Z", "user": 1, "content_type": 8, "object_id": "1", "object_repr": "Familia", "action_flag": 2, "change_message": "[{\"changed\": {\"fields\": [\"Logo\", \"Contenido\"]}}]"}}, {"model": "admin.logentry", "pk": 9, "fields": {"action_time": "2022-11-21T04:31:41.690Z", "user": 1, "content_type": 8, "object_id": "2", "object_repr": "manada", "action_flag": 2, "change_message": "[{\"changed\": {\"fields\": [\"Logo\"]}}]"}}, {"model": "admin.logentry", "pk": 10, "fields": {"action_time": "2022-11-21T04:34:51.977Z", "user": 1, "content_type": 8, "object_id": "2", "object_repr": "Manada", "action_flag": 2, "change_message": "[{\"changed\": {\"fields\": [\"Nombre o t\\u00edtulo\"]}}]"}}, {"model": "admin.logentry", "pk": 11, "fields": {"action_time": "2022-11-21T04:35:09.266Z", "user": 1, "content_type": 8, "object_id": "3", "object_repr": "Tropa", "action_flag": 1, "change_message": "[{\"added\": {}}]"}}, {"model": "admin.logentry", "pk": 12, "fields": {"action_time": "2022-11-21T04:36:22.210Z", "user": 1, "content_type": 8, "object_id": "1", "object_repr": "Familia", "action_flag": 2, "change_message": "[{\"changed\": {\"fields\": [\"Estado\"]}}]"}}, {"model": "admin.logentry", "pk": 13, "fields": {"action_time": "2022-11-21T04:36:38.381Z", "user": 1, "content_type": 8, "object_id": "1", "object_repr": "Familia", "action_flag": 2, "change_message": "[{\"changed\": {\"fields\": [\"Estado\"]}}]"}}, {"model": "admin.logentry", "pk": 14, "fields": {"action_time": "2022-11-21T04:37:47.446Z", "user": 1, "content_type": 8, "object_id": "4", "object_repr": "Clan", "action_flag": 1, "change_message": "[{\"added\": {}}]"}}, {"model": "admin.logentry", "pk": 15, "fields": {"action_time": "2022-11-21T04:38:27.412Z", "user": 1, "content_type": 8, "object_id": "5", "object_repr": "Jefatura", "action_flag": 1, "change_message": "[{\"added\": {}}]"}}, {"model": "admin.logentry", "pk": 16, "fields": {"action_time": "2022-11-21T04:38:57.615Z", "user": 1, "content_type": 8, "object_id": "6", "object_repr": "Consejo", "action_flag": 1, "change_message": "[{\"added\": {}}]"}}, {"model": "admin.logentry", "pk": 17, "fields": {"action_time": "2022-11-21T04:39:18.042Z", "user": 1, "content_type": 8, "object_id": "7", "object_repr": "Invitado", "action_flag": 1, "change_message": "[{\"added\": {}}]"}}, {"model": "admin.logentry", "pk": 18, "fields": {"action_time": "2022-11-21T04:39:34.520Z", "user": 1, "content_type": 8, "object_id": "8", "object_repr": "El que falta", "action_flag": 1, "change_message": "[{\"added\": {}}]"}}, {"model": "admin.logentry", "pk": 19, "fields": {"action_time": "2022-11-21T04:58:54.963Z", "user": 1, "content_type": 8, "object_id": "1", "object_repr": "Familia", "action_flag": 2, "change_message": "[{\"changed\": {\"fields\": [\"Contenido\"]}}]"}}, {"model": "admin.logentry", "pk": 20, "fields": {"action_time": "2022-11-21T04:59:00.248Z", "user": 1, "content_type": 8, "object_id": "2", "object_repr": "Manada", "action_flag": 2, "change_message": "[{\"changed\": {\"fields\": [\"Contenido\"]}}]"}}, {"model": "admin.logentry", "pk": 21, "fields": {"action_time": "2022-11-21T04:59:03.760Z", "user": 1, "content_type": 8, "object_id": "3", "object_repr": "Tropa", "action_flag": 2, "change_message": "[]"}}, {"model": "admin.logentry", "pk": 22, "fields": {"action_time": "2022-11-21T04:59:07.417Z", "user": 1, "content_type": 8, "object_id": "4", "object_repr": "Clan", "action_flag": 2, "change_message": "[]"}}, {"model": "admin.logentry", "pk": 23, "fields": {"action_time": "2022-11-21T04:59:12.117Z", "user": 1, "content_type": 8, "object_id": "4", "object_repr": "Clan", "action_flag": 2, "change_message": "[{\"changed\": {\"fields\": [\"Contenido\"]}}]"}}, {"model": "admin.logentry", "pk": 24, "fields": {"action_time": "2022-11-21T04:59:18.559Z", "user": 1, "content_type": 8, "object_id": "5", "object_repr": "Jefatura", "action_flag": 2, "change_message": "[{\"changed\": {\"fields\": [\"Contenido\"]}}]"}}, {"model": "admin.logentry", "pk": 25, "fields": {"action_time": "2022-11-21T04:59:21.744Z", "user": 1, "content_type": 8, "object_id": "6", "object_repr": "Consejo", "action_flag": 2, "change_message": "[]"}}, {"model": "admin.logentry", "pk": 26, "fields": {"action_time": "2022-11-21T04:59:25.048Z", "user": 1, "content_type": 8, "object_id": "7", "object_repr": "Invitado", "action_flag": 2, "change_message": "[]"}}, {"model": "admin.logentry", "pk": 27, "fields": {"action_time": "2022-11-21T04:59:27.849Z", "user": 1, "content_type": 8, "object_id": "8", "object_repr": "El que falta", "action_flag": 2, "change_message": "[]"}}, {"model": "admin.logentry", "pk": 28, "fields": {"action_time": "2022-11-21T05:25:51.673Z", "user": 1, "content_type": 7, "object_id": "2", "object_repr": "Noticia 2", "action_flag": 1, "change_message": "[{\"added\": {}}]"}}, {"model": "admin.logentry", "pk": 29, "fields": {"action_time": "2022-11-21T05:26:00.262Z", "user": 1, "content_type": 7, "object_id": "3", "object_repr": "Noticia 3", "action_flag": 1, "change_message": "[{\"added\": {}}]"}}, {"model": "admin.logentry", "pk": 30, "fields": {"action_time": "2022-11-21T05:26:07.736Z", "user": 1, "content_type": 7, "object_id": "4", "object_repr": "Noticia 4", "action_flag": 1, "change_message": "[{\"added\": {}}]"}}, {"model": "admin.logentry", "pk": 31, "fields": {"action_time": "2022-11-21T05:26:14.027Z", "user": 1, "content_type": 7, "object_id": "4", "object_repr": "Noticia 4", "action_flag": 2, "change_message": "[{\"changed\": {\"fields\": [\"Estado\"]}}]"}}, {"model": "admin.logentry", "pk": 32, "fields": {"action_time": "2022-11-21T05:28:03.163Z", "user": 1, "content_type": 7, "object_id": "4", "object_repr": "Noticia 4", "action_flag": 2, "change_message": "[{\"changed\": {\"fields\": [\"Estado\"]}}]"}}, {"model": "admin.logentry", "pk": 33, "fields": {"action_time": "2022-11-21T05:30:17.409Z", "user": 1, "content_type": 7, "object_id": "4", "object_repr": "Noticia 4", "action_flag": 2, "change_message": "[{\"changed\": {\"fields\": [\"Se muestra en el inicio\"]}}]"}}, {"model": "admin.logentry", "pk": 34, "fields": {"action_time": "2022-11-21T05:37:40.078Z", "user": 1, "content_type": 7, "object_id": "4", "object_repr": "Noticia 4", "action_flag": 2, "change_message": "[{\"changed\": {\"fields\": [\"Se muestra en el inicio\"]}}]"}}, {"model": "admin.logentry", "pk": 35, "fields": {"action_time": "2022-11-21T05:38:06.875Z", "user": 1, "content_type": 7, "object_id": "4", "object_repr": "Noticia 4", "action_flag": 2, "change_message": "[]"}}, {"model": "admin.logentry", "pk": 36, "fields": {"action_time": "2022-11-21T05:38:11.689Z", "user": 1, "content_type": 7, "object_id": "1", "object_repr": "Cuándo y cómo lavarse las manos", "action_flag": 2, "change_message": "[]"}}, {"model": "admin.logentry", "pk": 37, "fields": {"action_time": "2022-11-21T05:38:17.919Z", "user": 1, "content_type": 7, "object_id": "2", "object_repr": "Noticia 2", "action_flag": 2, "change_message": "[{\"changed\": {\"fields\": [\"Orden\"]}}]"}}, {"model": "admin.logentry", "pk": 38, "fields": {"action_time": "2022-11-21T05:38:30.290Z", "user": 1, "content_type": 7, "object_id": "2", "object_repr": "Noticia 2", "action_flag": 2, "change_message": "[{\"changed\": {\"fields\": [\"Orden\"]}}]"}}, {"model": "auth.permission", "pk": 1, "fields": {"name": "Can add log entry", "content_type": 1, "codename": "add_logentry"}}, {"model": "auth.permission", "pk": 2, "fields": {"name": "Can change log entry", "content_type": 1, "codename": "change_logentry"}}, {"model": "auth.permission", "pk": 3, "fields": {"name": "Can delete log entry", "content_type": 1, "codename": "delete_logentry"}}, {"model": "auth.permission", "pk": 4, "fields": {"name": "Can view log entry", "content_type": 1, "codename": "view_logentry"}}, {"model": "auth.permission", "pk": 5, "fields": {"name": "Can add permission", "content_type": 2, "codename": "add_permission"}}, {"model": "auth.permission", "pk": 6, "fields": {"name": "Can change permission", "content_type": 2, "codename": "change_permission"}}, {"model": "auth.permission", "pk": 7, "fields": {"name": "Can delete permission", "content_type": 2, "codename": "delete_permission"}}, {"model": "auth.permission", "pk": 8, "fields": {"name": "Can view permission", "content_type": 2, "codename": "view_permission"}}, {"model": "auth.permission", "pk": 9, "fields": {"name": "Can add group", "content_type": 3, "codename": "add_group"}}, {"model": "auth.permission", "pk": 10, "fields": {"name": "Can change group", "content_type": 3, "codename": "change_group"}}, {"model": "auth.permission", "pk": 11, "fields": {"name": "Can delete group", "content_type": 3, "codename": "delete_group"}}, {"model": "auth.permission", "pk": 12, "fields": {"name": "Can view group", "content_type": 3, "codename": "view_group"}}, {"model": "auth.permission", "pk": 13, "fields": {"name": "Can add content type", "content_type": 4, "codename": "add_contenttype"}}, {"model": "auth.permission", "pk": 14, "fields": {"name": "Can change content type", "content_type": 4, "codename": "change_contenttype"}}, {"model": "auth.permission", "pk": 15, "fields": {"name": "Can delete content type", "content_type": 4, "codename": "delete_contenttype"}}, {"model": "auth.permission", "pk": 16, "fields": {"name": "Can view content type", "content_type": 4, "codename": "view_contenttype"}}, {"model": "auth.permission", "pk": 17, "fields": {"name": "Can add session", "content_type": 5, "codename": "add_session"}}, {"model": "auth.permission", "pk": 18, "fields": {"name": "Can change session", "content_type": 5, "codename": "change_session"}}, {"model": "auth.permission", "pk": 19, "fields": {"name": "Can delete session", "content_type": 5, "codename": "delete_session"}}, {"model": "auth.permission", "pk": 20, "fields": {"name": "Can view session", "content_type": 5, "codename": "view_session"}}, {"model": "auth.permission", "pk": 21, "fields": {"name": "Can add Pagina | Inicio", "content_type": 6, "codename": "add_homemodel"}}, {"model": "auth.permission", "pk": 22, "fields": {"name": "Can change Pagina | Inicio", "content_type": 6, "codename": "change_homemodel"}}, {"model": "auth.permission", "pk": 23, "fields": {"name": "Can delete Pagina | Inicio", "content_type": 6, "codename": "delete_homemodel"}}, {"model": "auth.permission", "pk": 24, "fields": {"name": "Can view Pagina | Inicio", "content_type": 6, "codename": "view_homemodel"}}, {"model": "auth.permission", "pk": 25, "fields": {"name": "Can add Pagina | Noticia", "content_type": 7, "codename": "add_newsmodel"}}, {"model": "auth.permission", "pk": 26, "fields": {"name": "Can change Pagina | Noticia", "content_type": 7, "codename": "change_newsmodel"}}, {"model": "auth.permission", "pk": 27, "fields": {"name": "Can delete Pagina | Noticia", "content_type": 7, "codename": "delete_newsmodel"}}, {"model": "auth.permission", "pk": 28, "fields": {"name": "Can view Pagina | Noticia", "content_type": 7, "codename": "view_newsmodel"}}, {"model": "auth.permission", "pk": 29, "fields": {"name": "Can add Pagina | Unidad", "content_type": 8, "codename": "add_unitsmodel"}}, {"model": "auth.permission", "pk": 30, "fields": {"name": "Can change Pagina | Unidad", "content_type": 8, "codename": "change_unitsmodel"}}, {"model": "auth.permission", "pk": 31, "fields": {"name": "Can delete Pagina | Unidad", "content_type": 8, "codename": "delete_unitsmodel"}}, {"model": "auth.permission", "pk": 32, "fields": {"name": "Can view Pagina | Unidad", "content_type": 8, "codename": "view_unitsmodel"}}, {"model": "auth.permission", "pk": 33, "fields": {"name": "Can add Usuario", "content_type": 9, "codename": "add_usersmodel"}}, {"model": "auth.permission", "pk": 34, "fields": {"name": "Can change Usuario", "content_type": 9, "codename": "change_usersmodel"}}, {"model": "auth.permission", "pk": 35, "fields": {"name": "Can delete Usuario", "content_type": 9, "codename": "delete_usersmodel"}}, {"model": "auth.permission", "pk": 36, "fields": {"name": "Can view Usuario", "content_type": 9, "codename": "view_usersmodel"}}, {"model": "contenttypes.contenttype", "pk": 1, "fields": {"app_label": "admin", "model": "logentry"}}, {"model": "contenttypes.contenttype", "pk": 2, "fields": {"app_label": "auth", "model": "permission"}}, {"model": "contenttypes.contenttype", "pk": 3, "fields": {"app_label": "auth", "model": "group"}}, {"model": "contenttypes.contenttype", "pk": 4, "fields": {"app_label": "contenttypes", "model": "contenttype"}}, {"model": "contenttypes.contenttype", "pk": 5, "fields": {"app_label": "sessions", "model": "session"}}, {"model": "contenttypes.contenttype", "pk": 6, "fields": {"app_label": "inicio", "model": "homemodel"}}, {"model": "contenttypes.contenttype", "pk": 7, "fields": {"app_label": "noticias", "model": "newsmodel"}}, {"model": "contenttypes.contenttype", "pk": 8, "fields": {"app_label": "unidades", "model": "unitsmodel"}}, {"model": "contenttypes.contenttype", "pk": 9, "fields": {"app_label": "usuarios", "model": "usersmodel"}}, {"model": "sessions.session", "pk": "nbbjjs033oli87jrca4jtm8c022wq4ar", "fields": {"session_data": ".eJxVjMsOwiAURP-FtSHQyqW6dN9vIPcBUjWQlHZl_HfbpAtNZjXnzLxVwHXJYW1xDpOoq7Lq9NsR8jOWHcgDy71qrmWZJ9K7og_a9Fglvm6H-3eQseVtjYk9XcgjJGe2nB0aC2B6AQEiC4YdORDsRJJJDH5wsWeMg0fqyKrPF_njOK0:1owvfB:Z3kWeGYQdTe1kDoewPzGny9Pc-YJ_4Wh6atRoc6MXG8", "expire_date": "2022-12-05T01:31:57.339Z"}}, {"model": "inicio.homemodel", "pk": 1, "fields": {"section_name": "Página de inicio", "created": "2022-11-21T03:46:48.875Z", "updated": "2022-11-21T04:31:24.410Z", "order": 0, "is_active": true, "video_link": "https://www.youtube.com/embed/0sYUAfZHdBY", "unit": 1, "img_content": "", "content": "<h3>El grupo Scout &quot;V Kenya&quot;</h3>\r\n\r\n<p>Cambio La naturaleza es un patio de recreo de los Scouts. Un lugar para descubrir cosas nuevas y embarcarse en grandes aventuras. Un lugar donde los j&oacute;venes adquieren habilidades de liderazgo al guiar a sus compa&ntilde;eros en aventuras significativas al aire libre.</p>", "news": 1}}, {"model": "noticias.newsmodel", "pk": 1, "fields": {"section_name": "Cuándo y cómo lavarse las manos", "created": "2022-11-21T03:46:45.370Z", "updated": "2022-11-21T05:38:11.687Z", "order": 0, "is_active": true, "home_active": true, "img": "", "content": "<p>Donec rutrum congue leo eget malesuada. Nulla quis lorem ut libero malesuada feugiat. Curabitur arcu erat, accumsan id imperdiet et, porttitor at sem. Praesent sapien massa, convallis a pellentesque nec, egestas non nisi.</p>\r\n\r\n<p>Mauris blandit aliquet elit, eget tincidunt nibh pulvinar a. Vivamus magna justo, lacinia eget consectetur sed, convallis at tellus. Pellentesque in ipsum id orci porta dapibus. Vivamus suscipit tortor eget felis porttitor volutpat.</p>\r\n\r\n<p>Praesent sapien massa, convallis a pellentesque nec, egestas non nisi. Quisque velit nisi, pretium ut lacinia in, elementum id enim. Quisque velit nisi, pretium ut lacinia in, elementum id enim. Curabitur non nulla sit amet nisl tempus convallis quis ac lectus.</p>", "home_visible": true}}, {"model": "noticias.newsmodel", "pk": 2, "fields": {"section_name": "Noticia 2", "created": "2022-11-21T05:25:51.670Z", "updated": "2022-11-21T05:38:30.288Z", "order": 0, "is_active": true, "home_active": true, "img": "", "content": "<p>Nulla quis lorem ut libero malesuada feugiat. Vestibulum ante ipsum primis in faucibus orci luctus et ultrices posuere cubilia Curae; Donec velit neque, auctor sit amet aliquam vel, ullamcorper sit amet ligula. Curabitur aliquet quam id dui posuere blandit. Curabitur non nulla sit amet nisl tempus convallis quis ac lectus.</p>\r\n\r\n<p>Curabitur aliquet quam id dui posuere blandit. Praesent sapien massa, convallis a pellentesque nec, egestas non nisi. Quisque velit nisi, pretium ut lacinia in, elementum id enim. Curabitur arcu erat, accumsan id imperdiet et, porttitor at sem.</p>\r\n\r\n<p>Donec rutrum congue leo eget malesuada. Vestibulum ac diam sit amet quam vehicula elementum sed sit amet dui. Vivamus magna justo, lacinia eget consectetur sed, convallis at tellus. Pellentesque in ipsum id orci porta dapibus.</p>", "home_visible": true}}, {"model": "noticias.newsmodel", "pk": 3, "fields": {"section_name": "Noticia 3", "created": "2022-11-21T05:26:00.257Z", "updated": "2022-11-21T05:26:00.258Z", "order": 0, "is_active": true, "home_active": true, "img": "", "content": "<p>Nulla quis lorem ut libero malesuada feugiat. Vestibulum ante ipsum primis in faucibus orci luctus et ultrices posuere cubilia Curae; Donec velit neque, auctor sit amet aliquam vel, ullamcorper sit amet ligula. Curabitur aliquet quam id dui posuere blandit. Curabitur non nulla sit amet nisl tempus convallis quis ac lectus.</p>\r\n\r\n<p>Curabitur aliquet quam id dui posuere blandit. Praesent sapien massa, convallis a pellentesque nec, egestas non nisi. Quisque velit nisi, pretium ut lacinia in, elementum id enim. Curabitur arcu erat, accumsan id imperdiet et, porttitor at sem.</p>\r\n\r\n<p>Donec rutrum congue leo eget malesuada. Vestibulum ac diam sit amet quam vehicula elementum sed sit amet dui. Vivamus magna justo, lacinia eget consectetur sed, convallis at tellus. Pellentesque in ipsum id orci porta dapibus.</p>", "home_visible": true}}, {"model": "noticias.newsmodel", "pk": 4, "fields": {"section_name": "Noticia 4", "created": "2022-11-21T05:26:07.734Z", "updated": "2022-11-21T05:38:06.871Z", "order": 0, "is_active": true, "home_active": true, "img": "", "content": "<p>Nulla quis lorem ut libero malesuada feugiat. Vestibulum ante ipsum primis in faucibus orci luctus et ultrices posuere cubilia Curae; Donec velit neque, auctor sit amet aliquam vel, ullamcorper sit amet ligula. Curabitur aliquet quam id dui posuere blandit. Curabitur non nulla sit amet nisl tempus convallis quis ac lectus.</p>\r\n\r\n<p>Curabitur aliquet quam id dui posuere blandit. Praesent sapien massa, convallis a pellentesque nec, egestas non nisi. Quisque velit nisi, pretium ut lacinia in, elementum id enim. Curabitur arcu erat, accumsan id imperdiet et, porttitor at sem.</p>\r\n\r\n<p>Donec rutrum congue leo eget malesuada. Vestibulum ac diam sit amet quam vehicula elementum sed sit amet dui. Vivamus magna justo, lacinia eget consectetur sed, convallis at tellus. Pellentesque in ipsum id orci porta dapibus.</p>", "home_visible": true}}, {"model": "unidades.unitsmodel", "pk": 1, "fields": {"section_name": "Familia", "created": "2022-11-21T03:45:15.785Z", "updated": "2022-11-21T04:58:54.960Z", "order": 0, "is_active": true, "logo_img": "", "content": "<p>Contenido familia</p>"}}, {"model": "unidades.unitsmodel", "pk": 2, "fields": {"section_name": "Manada", "created": "2022-11-21T04:22:59.491Z", "updated": "2022-11-21T04:59:00.245Z", "order": 0, "is_active": true, "logo_img": "", "content": "<p>Contenido manada</p>"}}, {"model": "unidades.unitsmodel", "pk": 3, "fields": {"section_name": "Tropa", "created": "2022-11-21T04:35:09.263Z", "updated": "2022-11-21T04:59:03.758Z", "order": 0, "is_active": true, "logo_img": "", "content": "<p>Contenido tropa</p>"}}, {"model": "unidades.unitsmodel", "pk": 4, "fields": {"section_name": "Clan", "created": "2022-11-21T04:37:47.442Z", "updated": "2022-11-21T04:59:12.114Z", "order": 0, "is_active": true, "logo_img": "", "content": "<p>Contenido clan</p>"}}, {"model": "unidades.unitsmodel", "pk": 5, "fields": {"section_name": "Jefatura", "created": "2022-11-21T04:38:27.409Z", "updated": "2022-11-21T04:59:18.556Z", "order": 0, "is_active": true, "logo_img": "", "content": "<p>Contenido jefatura</p>"}}, {"model": "unidades.unitsmodel", "pk": 6, "fields": {"section_name": "Consejo", "created": "2022-11-21T04:38:57.613Z", "updated": "2022-11-21T04:59:21.741Z", "order": 0, "is_active": true, "logo_img": "", "content": "<p>Contenido consejo</p>"}}, {"model": "unidades.unitsmodel", "pk": 7, "fields": {"section_name": "Invitado", "created": "2022-11-21T04:39:18.040Z", "updated": "2022-11-21T04:59:25.047Z", "order": 0, "is_active": true, "logo_img": "", "content": "<p>Contenido invitado</p>"}}, {"model": "unidades.unitsmodel", "pk": 8, "fields": {"section_name": "El que falta", "created": "2022-11-21T04:39:34.517Z", "updated": "2022-11-21T04:59:27.846Z", "order": 0, "is_active": true, "logo_img": "", "content": "<p>Contenido del que falta</p>"}}, {"model": "usuarios.usersmodel", "pk": 1, "fields": {"password": "pbkdf2_sha256$390000$CCKS7Ui9kySmBZHNYosnjM$cq/y9+Oan6AFrK4BFKwrrHLPC8Su6+/zAdIhyY2oNdk=", "last_login": "2022-11-21T01:31:57.334Z", "is_superuser": true, "username": "sebasmd", "is_staff": true, "date_joined": "2022-11-21T01:31:50.413Z", "full_name": "Juan Sebastian Morales Delgado", "first_name": "Juan Sebastian", "last_name": "Morales Delgado", "birthday": "1999-05-16", "age": 23, "email": "sebastian@sebasmd.com", "document_type": "CC", "document_number": "", "order": 0, "role": "US", "gender": "O", "is_active": true, "groups": [], "user_permissions": []}}]